demoparser-0.4.0.dist-info/METADATA
demoparser-0.4.0.dist-info/WHEEL
demoparser/__init__.py
demoparser/demoparser.cpython-311-x86_64-linux-gnu.so
demoparser-0.4.0.dist-info/RECORD
