Metadata-Version: 2.1
Name: demoparser
Version: 0.4.0
Classifier: Programming Language :: Rust
Classifier: Programming Language :: Python :: Implementation :: CPython
Classifier: Programming Language :: Python :: Implementation :: PyPy
Requires-Dist: pandas
Requires-Dist: numpy
Requires-Dist: polars
Requires-Dist: pyarrow
Requires-Dist: tqdm
Requires-Python: >=3.7
